neon_messagebus/__init__.py
neon_messagebus/cli.py
neon_messagebus/service/__init__.py
neon_messagebus/service/__main__.py
neon_messagebus/util/__init__.py
neon_messagebus/util/config.py
neon_messagebus/util/message_utils.py
neon_messagebus/util/mq_connector.py
neon_messagebus/util/signal_utils.py
neon_messagebus-2.1.0.dist-info/LICENSE.md
neon_messagebus-2.1.0.dist-info/METADATA
neon_messagebus-2.1.0.dist-info/WHEEL
neon_messagebus-2.1.0.dist-info/entry_points.txt
neon_messagebus-2.1.0.dist-info/top_level.txt
neon_messagebus-2.1.0.dist-info/RECORD
