Metadata-Version: 2.1
Name: neon-messagebus
Version: 2.1.0
Summary: Neon Messagebus Module
Home-page: https://github.com/NeonGeckoCom/neon_messagebus
Author: Neongecko
Author-email: developers@neon.ai
License: BSD-3-Clause
License-File: LICENSE.md
Requires-Dist: neon-messagebus-mq-connector~=1.0
Requires-Dist: neon-mq-connector~=0.9
Requires-Dist: ovos-messagebus~=0.0.4
Requires-Dist: ovos-utils>=0.0.32,~=0.0
Requires-Dist: ovos-config~=0.1
Requires-Dist: ovos-bus-client>=0.0.6,~=0.0
Requires-Dist: tornado>=6.0.3,~=6.0
Requires-Dist: neon-utils[network]~=1.6
Requires-Dist: click~=8.0
Requires-Dist: click-default-group~=1.2
Provides-Extra: docker
Requires-Dist: neon-mana-utils~=0.2; extra == "docker"
Requires-Dist: neon-utils[sentry]~=1.12; extra == "docker"
